{"file":"boxrewardpopupview.png","frames":{"boxrewardbulltebg":{"x":2,"y":575,"w":265,"h":146,"offX":0,"offY":0,"sourceW":265,"sourceH":146},"boxrewarddetailpopupviewbg":{"x":2,"y":2,"w":571,"h":571,"offX":0,"offY":0,"sourceW":571,"sourceH":571},"dicecardlevel1":{"x":425,"y":625,"w":44,"h":48,"offX":2,"offY":1,"sourceW":50,"sourceH":50},"dicecardlevel2":{"x":396,"y":575,"w":44,"h":48,"offX":2,"offY":1,"sourceW":50,"sourceH":50},"dicecardlevel3":{"x":379,"y":643,"w":44,"h":48,"offX":2,"offY":1,"sourceW":50,"sourceH":50},"dicecardlevel4":{"x":333,"y":643,"w":44,"h":48,"offX":2,"offY":1,"sourceW":50,"sourceH":50},"dicestreelight2":{"x":269,"y":643,"w":62,"h":66,"offX":0,"offY":0,"sourceW":62,"sourceH":66},"dicestreelight3":{"x":269,"y":575,"w":62,"h":66,"offX":0,"offY":0,"sourceW":62,"sourceH":66},"dicestreelight4":{"x":333,"y":575,"w":61,"h":66,"offX":0,"offY":0,"sourceW":61,"sourceH":66}}}