{"width":1024,"SubTexture":[{"width":108,"y":220,"height":134,"name":"yuxi","x":701},{"width":70,"y":371,"height":65,"name":"youshou","x":470},{"width":30,"y":584,"height":51,"name":"zhi4","x":572},{"width":32,"y":584,"height":50,"name":"zhi3","x":540},{"width":27,"y":915,"height":48,"name":"zhi2","x":352},{"width":24,"y":915,"height":39,"name":"zhi1","x":416},{"frameWidth":90,"y":799,"frameHeight":222,"width":88,"frameX":-1,"height":220,"name":"youbi","frameY":-1,"x":606},{"width":108,"y":642,"height":306,"name":"xiuzihou","x":498},{"frameWidth":68,"y":545,"frameHeight":182,"width":66,"frameX":-1,"height":180,"name":"youbi2","frameY":-1,"x":687},{"width":119,"y":153,"height":302,"name":"xiuziqian","x":351},{"width":41,"y":915,"height":107,"name":"houyi3","x":311},{"width":184,"y":0,"height":378,"name":"yi2","x":151},{"width":70,"y":354,"height":134,"name":"houyi2","x":714},{"frameWidth":58,"y":545,"frameHeight":41,"width":56,"frameX":-1,"height":39,"name":"houyi","frameY":-1,"x":540},{"frameWidth":21,"y":1002,"frameHeight":23,"width":19,"frameX":-1,"height":21,"name":"houling","frameY":-1,"x":202},{"width":80,"y":912,"height":90,"name":"bo","x":158},{"width":254,"y":0,"height":153,"name":"qun","x":335},{"width":163,"y":655,"height":260,"name":"body","x":335},{"width":189,"y":455,"height":187,"name":"yao","x":351},{"width":142,"y":153,"height":218,"name":"face","x":470},{"width":56,"y":1002,"height":20,"name":"yanpi","x":146},{"width":156,"y":655,"height":257,"name":"zuobi","x":158},{"width":158,"y":537,"height":447,"name":"youyi","x":0},{"width":81,"y":545,"height":254,"name":"dai1","x":606},{"width":174,"y":371,"height":174,"name":"zhui1","x":540},{"width":151,"y":0,"height":537,"name":"zuoyi","x":0},{"width":89,"y":0,"height":307,"name":"dai2","x":612},{"width":121,"y":0,"height":220,"name":"zhui2","x":701},{"width":193,"y":378,"height":277,"name":"zuoxiu","x":158},{"width":73,"y":912,"height":90,"name":"zuoshou","x":238},{"width":75,"y":307,"height":54,"name":"zuozhi4","x":612},{"width":79,"y":984,"height":31,"name":"zuozhi3","x":67},{"width":67,"y":984,"height":37,"name":"zuozhi2","x":0},{"width":37,"y":915,"height":35,"name":"zuozhi1","x":379}],"height":1024,"name":"servant_full2_20021","imagePath":"servant_full2_20021_tex.png"}