{"file":"mainlangcity1.png","frames":{"mainland_armystate_redtitle":{"x":2,"y":213,"w":599,"h":131,"offX":0,"offY":0,"sourceW":599,"sourceH":131},"mainland_cityitem_noarmy":{"x":103,"y":346,"w":137,"h":146,"offX":0,"offY":0,"sourceW":137,"sourceH":146},"mainland_sendfight_itembg":{"x":2,"y":346,"w":99,"h":205,"offX":0,"offY":0,"sourceW":99,"sourceH":205},"mainland_sendfight_topbg":{"x":2,"y":145,"w":623,"h":66,"offX":0,"offY":0,"sourceW":623,"sourceH":66},"mainland_warshow_titlebg-1":{"x":2,"y":2,"w":640,"h":141,"offX":0,"offY":0,"sourceW":640,"sourceH":141}}}