{
"texture":"newParticle.png",
"startBlueVariance":0
,"radialAcceleration":0
,"emitter":{"x":754,"y":318}
,"radialAccelerationVariance":0
,"duration":-1
,"endSizeVariance":31
,"blendFactorSource":"one"
,"endBlue":255
,"tangentialAccelerationVariance":0
,"startAlphaVariance":0
,"tangentialAcceleration":0
,"maxRadiusVariance":30
,"lifespan":600
,"blendFactorDestination":"oneMinusSourceAlpha"
,"minRadius":20
,"lifespanVariance":600
,"maxRadius":100
,"engGreenVariance":0
,"startSize":0
,"maxParticles":200
,"rotatePerSecond":30
,"startSizeVariance":30
,"startRedVariance":0
,"rotatePerSecondVariance":10
,"endSize":18
,"minRadiusVariance":10
,"emitterType":0
,"emitAngle":180
,"startRed":255
,"emitAngleVariance":360
,"endAlphaVariance":0
,"startRotation":153
,"startAlpha":1
,"endGreen":255
,"endRedVariance":0
,"emitterVariance":{"x":1,"y":1}
,"endRotation":263.58
,"endBlueVariance":0
,"speed":77
,"endRotationVariance":292.07
,"startGreenVariance":0
,"startGreen":255
,"gravity":{"x":0,"y":0}
,"speedVariance":0
,"endAlpha":1
,"startBlue":255
,"endRed":255
,"startRotationVariance":163
}