{"file":"acblessingofmammoncode3.png","frames":{"acblessingofmammon_bigbox-3":{"x":256,"y":391,"w":143,"h":141,"offX":0,"offY":0,"sourceW":143,"sourceH":141},"acblessingofmammon_box1-3":{"x":260,"y":85,"w":122,"h":148,"offX":7,"offY":5,"sourceW":132,"sourceH":160},"acblessingofmammon_box2-3":{"x":254,"y":241,"w":122,"h":148,"offX":7,"offY":5,"sourceW":132,"sourceH":160},"acblessingofmammon_box3-3":{"x":132,"y":397,"w":122,"h":148,"offX":7,"offY":5,"sourceW":132,"sourceH":160},"acblessingofmammon_box4-3":{"x":132,"y":241,"w":120,"h":154,"offX":3,"offY":3,"sourceW":132,"sourceH":160},"acblessingofmammon_boxlight1-3":{"x":2,"y":403,"w":128,"h":154,"offX":4,"offY":2,"sourceW":132,"sourceH":160},"acblessingofmammon_boxlight2-3":{"x":130,"y":85,"w":128,"h":154,"offX":4,"offY":2,"sourceW":132,"sourceH":160},"acblessingofmammon_boxlight3-3":{"x":2,"y":247,"w":128,"h":154,"offX":4,"offY":2,"sourceW":132,"sourceH":160},"acblessingofmammon_boxlight4-3":{"x":2,"y":85,"w":126,"h":160,"offX":0,"offY":0,"sourceW":132,"sourceH":160},"acblessingofmammon_chargenumbg-3":{"x":2,"y":2,"w":640,"h":81,"offX":0,"offY":0,"sourceW":640,"sourceH":81},"acblessingofmammon_line_1-3":{"x":105,"y":559,"w":95,"h":73,"offX":3,"offY":3,"sourceW":101,"sourceH":79},"acblessingofmammon_line_2-3":{"x":2,"y":559,"w":101,"h":79,"offX":0,"offY":0,"sourceW":101,"sourceH":79},"acblessingofmammon_table-3":{"x":202,"y":547,"w":195,"h":69,"offX":0,"offY":0,"sourceW":195,"sourceH":69}}}