{"file":"invitefriendview.png","frames":{"invitefriendbg":{"x":2,"y":2,"w":606,"h":769,"offX":0,"offY":0,"sourceW":606,"sourceH":769},"invitefriendcodebg":{"x":938,"y":581,"w":215,"h":49,"offX":0,"offY":0,"sourceW":215,"sourceH":49},"invitefriendcodekuang":{"x":610,"y":738,"w":184,"h":45,"offX":0,"offY":0,"sourceW":184,"sourceH":45},"invitefriendcopybtn":{"x":975,"y":770,"w":177,"h":74,"offX":0,"offY":0,"sourceW":177,"sourceH":74},"invitefriendrewardbg":{"x":2,"y":846,"w":124,"h":127,"offX":0,"offY":0,"sourceW":124,"sourceH":127},"invitefriendscorebg":{"x":938,"y":541,"w":235,"h":38,"offX":0,"offY":0,"sourceW":235,"sourceH":38},"invitefriendsharebtn":{"x":796,"y":770,"w":177,"h":74,"offX":0,"offY":0,"sourceW":177,"sourceH":74},"invitefriendtabbg":{"x":890,"y":716,"w":185,"h":52,"offX":1,"offY":11,"sourceW":187,"sourceH":82},"invitefriendtabbg_down":{"x":938,"y":632,"w":187,"h":82,"offX":0,"offY":0,"sourceW":187,"sourceH":82},"invitefriendtipbg":{"x":610,"y":2,"w":574,"h":537,"offX":0,"offY":0,"sourceW":574,"sourceH":537},"invitefriendtiptop":{"x":610,"y":652,"w":278,"h":84,"offX":0,"offY":0,"sourceW":278,"sourceH":84},"invitefriendtitle":{"x":610,"y":541,"w":326,"h":109,"offX":0,"offY":0,"sourceW":326,"sourceH":109},"invitefriendwordbg":{"x":1127,"y":632,"w":44,"h":44,"offX":0,"offY":0,"sourceW":44,"sourceH":44}}}