{"SubTexture":[{"width":242,"y":1,"height":467,"name":"xue_22","x":1},{"width":72,"y":1,"height":133,"name":"xue_21","x":827},{"width":88,"y":308,"height":168,"name":"xue_20","x":907},{"width":96,"y":143,"height":163,"name":"xue_19","x":907},{"width":144,"y":1,"height":140,"name":"xue_18","x":681},{"width":144,"y":372,"height":126,"name":"xue_17","x":493},{"width":39,"y":347,"height":23,"name":"xue_16","x":493},{"width":106,"y":1,"height":376,"name":"xue_15","x":245},{"width":79,"y":1,"height":369,"name":"xue_14","x":600},{"width":112,"y":1,"height":83,"name":"xue_13","x":901},{"width":131,"y":1,"height":279,"name":"xue_12","x":353},{"width":78,"y":379,"height":111,"name":"xue_11","x":245},{"width":90,"y":281,"height":64,"name":"xue_10","x":493},{"width":112,"y":1,"height":278,"name":"xue_9","x":486},{"width":133,"y":372,"height":130,"name":"xue_8","x":639},{"width":131,"y":372,"height":128,"name":"xue_7","x":774},{"width":14,"y":478,"height":33,"name":"xue_6","x":961},{"width":14,"y":478,"height":33,"name":"xue_5","x":945},{"width":138,"y":282,"height":168,"name":"xue_4","x":353},{"width":36,"y":347,"height":18,"name":"xue_3","x":534},{"width":36,"y":478,"height":18,"name":"xue_2","x":907},{"width":10,"y":281,"height":42,"name":"xue_1","x":585}],"width":1024,"imagePath":"wife_full_203_tex.png","name":"wife_full_203","height":1024}