{"width":1024,"SubTexture":[{"width":163,"y":507,"height":41,"name":"haungzhong_44","x":441},{"width":47,"y":301,"height":49,"name":"haungzhong_43","x":759},{"width":130,"y":429,"height":43,"name":"haungzhong_42","x":699},{"width":113,"y":258,"height":41,"name":"haungzhong_41","x":703},{"width":99,"y":429,"height":76,"name":"haungzhong_40","x":598},{"width":62,"y":625,"height":92,"name":"haungzhong_39","x":585},{"width":25,"y":258,"height":23,"name":"haungzhong_38","x":637},{"width":49,"y":524,"height":67,"name":"haungzhong_37","x":260},{"width":126,"y":429,"height":127,"name":"haungzhong_36","x":313},{"width":32,"y":815,"height":76,"name":"haungzhong_35","x":130},{"width":70,"y":932,"height":87,"name":"haungzhong_34","x":66},{"width":155,"y":429,"height":50,"name":"haungzhong_33","x":441},{"width":54,"y":301,"height":52,"name":"haungzhong_32","x":703},{"width":201,"y":2,"height":286,"name":"haungzhong_31","x":434},{"width":67,"y":612,"height":90,"name":"haungzhong_30","x":516},{"width":43,"y":979,"height":41,"name":"haungzhong_29","x":2},{"width":87,"y":460,"height":62,"name":"haungzhong_28","x":222},{"frameWidth":99,"y":593,"frameHeight":104,"width":97,"frameX":-1,"height":103,"name":"haungzhong_27","frameY":-1,"x":105},{"width":39,"y":164,"height":58,"name":"haungzhong_26","x":864},{"frameWidth":18,"y":979,"frameHeight":20,"width":16,"frameX":-1,"height":18,"name":"haungzhong_25","frameY":-1,"x":47},{"width":22,"y":778,"height":29,"name":"haungzhong_24","x":66},{"width":25,"y":893,"height":29,"name":"haungzhong_23","x":130},{"width":22,"y":744,"height":32,"name":"haungzhong_22","x":66},{"frameWidth":194,"y":352,"frameHeight":11,"width":194,"frameX":0,"height":10,"name":"gong5","frameY":0,"x":759},{"width":193,"y":332,"height":8,"name":"gong4","x":808},{"width":125,"y":625,"height":45,"name":"gong3","x":649},{"width":65,"y":698,"height":115,"name":"gong2","x":105},{"width":301,"y":558,"height":52,"name":"gong1","x":313},{"width":430,"y":2,"height":324,"name":"haungzhong_20","x":2},{"width":173,"y":328,"height":103,"name":"haungzhong_19","x":2},{"width":110,"y":460,"height":84,"name":"haungzhong_18","x":110},{"width":54,"y":546,"height":158,"name":"haungzhong_17","x":204},{"width":267,"y":290,"height":137,"name":"piaodai","x":434},{"width":106,"y":433,"height":158,"name":"haungzhong_11","x":2},{"width":62,"y":258,"height":72,"name":"haungzhong_9","x":818},{"width":20,"y":258,"height":23,"name":"haungzhong_8","x":664},{"width":23,"y":524,"height":19,"name":"haungzhong_7","x":222},{"frameWidth":102,"y":593,"frameHeight":151,"width":101,"frameX":-1,"height":149,"name":"haungzhong_6","frameY":-1,"x":2},{"width":134,"y":328,"height":130,"name":"haungzhong_5","x":177},{"width":117,"y":328,"height":95,"name":"haungzhong_4","x":313},{"frameWidth":144,"y":2,"frameHeight":162,"width":143,"frameX":-1,"height":160,"name":"haungzhong_3","frameY":-1,"x":637},{"width":225,"y":164,"height":92,"name":"haungzhong_2","x":637},{"width":215,"y":2,"height":91,"name":"haungzhong_1","x":782},{"frameWidth":197,"y":95,"frameHeight":67,"width":195,"frameX":0,"height":67,"name":"haungzhong_0","frameY":0,"x":782},{"width":18,"y":612,"height":8,"name":"biyan1","x":585},{"width":12,"y":999,"height":11,"name":"biyan2","x":47},{"frameWidth":70,"y":612,"frameHeight":125,"width":62,"frameX":-5,"height":115,"name":"jianguang_02","frameY":-6,"x":324},{"frameWidth":70,"y":815,"frameHeight":125,"width":62,"frameX":-5,"height":115,"name":"jianguang_09","frameY":-6,"x":66},{"frameWidth":70,"y":612,"frameHeight":125,"width":62,"frameX":-5,"height":116,"name":"jianguang_05","frameY":-6,"x":260},{"frameWidth":70,"y":862,"frameHeight":125,"width":62,"frameX":-5,"height":115,"name":"jianguang_00","frameY":-6,"x":2},{"frameWidth":70,"y":706,"frameHeight":125,"width":62,"frameX":-5,"height":115,"name":"jianguang_03","frameY":-6,"x":172},{"frameWidth":70,"y":612,"frameHeight":125,"width":62,"frameX":-5,"height":115,"name":"jianguang_08","frameY":-6,"x":388},{"frameWidth":70,"y":507,"frameHeight":125,"width":62,"frameX":-5,"height":116,"name":"jianguang_04","frameY":-6,"x":616},{"frameWidth":70,"y":823,"frameHeight":125,"width":62,"frameX":-5,"height":115,"name":"jianguang_01","frameY":-6,"x":172},{"frameWidth":70,"y":612,"frameHeight":125,"width":62,"frameX":-5,"height":115,"name":"jianguang_07","frameY":-6,"x":452},{"frameWidth":70,"y":744,"frameHeight":125,"width":62,"frameX":-5,"height":116,"name":"jianguang_06","frameY":-6,"x":2}],"height":1024,"name":"servant_full2_20181","imagePath":"servant_full2_20181_tex.png"}