{"file":"composeeffect21.png","frames":{"composeeffect21_1":{"x":268,"y":124,"w":64,"h":120,"offX":20,"offY":21,"sourceW":100,"sourceH":150},"composeeffect21_10":{"x":202,"y":124,"w":64,"h":120,"offX":19,"offY":21,"sourceW":100,"sourceH":150},"composeeffect21_2":{"x":136,"y":124,"w":64,"h":120,"offX":19,"offY":21,"sourceW":100,"sourceH":150},"composeeffect21_3":{"x":2,"y":126,"w":64,"h":122,"offX":18,"offY":19,"sourceW":100,"sourceH":150},"composeeffect21_4":{"x":270,"y":2,"w":64,"h":120,"offX":18,"offY":21,"sourceW":100,"sourceH":150},"composeeffect21_5":{"x":136,"y":2,"w":66,"h":120,"offX":16,"offY":21,"sourceW":100,"sourceH":150},"composeeffect21_6":{"x":68,"y":124,"w":66,"h":120,"offX":16,"offY":21,"sourceW":100,"sourceH":150},"composeeffect21_7":{"x":68,"y":2,"w":66,"h":120,"offX":16,"offY":21,"sourceW":100,"sourceH":150},"composeeffect21_8":{"x":2,"y":2,"w":64,"h":122,"offX":18,"offY":19,"sourceW":100,"sourceH":150},"composeeffect21_9":{"x":204,"y":2,"w":64,"h":120,"offX":18,"offY":21,"sourceW":100,"sourceH":150}}}