{"width":256,"imagePath":"wife_tex.png","height":256,"name":"wife","SubTexture":[{"width":94,"y":1,"height":224,"name":"she-ti","x":1},{"width":10,"y":1,"height":57,"name":"piao-dai-01","x":238},{"width":10,"y":52,"height":52,"name":"piao-dai-02","x":222},{"width":9,"y":106,"height":49,"name":"piao-dai-03","x":222},{"width":26,"y":189,"height":59,"name":"zuo-jian","x":165},{"width":21,"y":79,"height":108,"name":"zuo-qun","x":132},{"width":28,"y":161,"height":78,"name":"you-qun","x":97},{"width":27,"y":189,"height":47,"name":"you-jian","x":193},{"width":14,"y":1,"height":72,"name":"you-fa","x":143},{"width":2,"y":161,"height":12,"name":"er-huan","x":127},{"width":14,"y":1,"height":49,"name":"zuo-fa","x":222},{"width":36,"y":189,"height":48,"name":"tou","x":127},{"width":33,"y":79,"height":80,"name":"zuo-bi","x":97},{"width":33,"y":227,"height":25,"name":"shou","x":1},{"width":44,"y":1,"height":76,"name":"you-bi","x":97},{"width":2,"y":239,"height":6,"name":"diao-zhui-01","x":127},{"width":3,"y":175,"height":8,"name":"diao-zhui-02","x":127},{"width":2,"y":241,"height":5,"name":"diao-zhui-03","x":131}]}