{"file":"wifebattlebattle_anim.png","frames":{"wifebattlebattle_anim1":{"x":2,"y":364,"w":360,"h":360,"offX":0,"offY":0,"sourceW":360,"sourceH":360},"wifebattlebattle_anim10":{"x":708,"y":2,"w":340,"h":306,"offX":5,"offY":40,"sourceW":360,"sourceH":360},"wifebattlebattle_anim11":{"x":364,"y":2,"w":342,"h":314,"offX":3,"offY":35,"sourceW":360,"sourceH":360},"wifebattlebattle_anim12":{"x":2,"y":726,"w":342,"h":310,"offX":3,"offY":36,"sourceW":360,"sourceH":360},"wifebattlebattle_anim13":{"x":364,"y":318,"w":340,"h":310,"offX":4,"offY":34,"sourceW":360,"sourceH":360},"wifebattlebattle_anim2":{"x":2,"y":1038,"w":246,"h":204,"offX":61,"offY":79,"sourceW":360,"sourceH":360},"wifebattlebattle_anim3":{"x":346,"y":930,"w":320,"h":298,"offX":24,"offY":29,"sourceW":360,"sourceH":360},"wifebattlebattle_anim4":{"x":2,"y":2,"w":360,"h":360,"offX":0,"offY":0,"sourceW":360,"sourceH":360},"wifebattlebattle_anim5":{"x":982,"y":878,"w":262,"h":250,"offX":47,"offY":66,"sourceW":360,"sourceH":360},"wifebattlebattle_anim6":{"x":696,"y":878,"w":284,"h":266,"offX":36,"offY":58,"sourceW":360,"sourceH":360},"wifebattlebattle_anim7":{"x":706,"y":600,"w":302,"h":276,"offX":27,"offY":54,"sourceW":360,"sourceH":360},"wifebattlebattle_anim8":{"x":708,"y":310,"w":318,"h":288,"offX":19,"offY":48,"sourceW":360,"sourceH":360},"wifebattlebattle_anim9":{"x":364,"y":630,"w":330,"h":298,"offX":12,"offY":44,"sourceW":360,"sourceH":360}}}