{"file":"ac_ransackTraitor_ani.png","frames":{"ac_ransackTraitor_ani1":{"x":2,"y":328,"w":344,"h":340,"offX":32,"offY":41,"sourceW":400,"sourceH":400},"ac_ransackTraitor_ani10":{"x":770,"y":1046,"w":356,"h":372,"offX":44,"offY":27,"sourceW":400,"sourceH":400},"ac_ransackTraitor_ani11":{"x":350,"y":682,"w":356,"h":350,"offX":35,"offY":30,"sourceW":400,"sourceH":400},"ac_ransackTraitor_ani12":{"x":980,"y":2,"w":326,"h":330,"offX":26,"offY":33,"sourceW":400,"sourceH":400},"ac_ransackTraitor_ani13":{"x":334,"y":2,"w":322,"h":324,"offX":47,"offY":48,"sourceW":400,"sourceH":400},"ac_ransackTraitor_ani14":{"x":2,"y":672,"w":346,"h":348,"offX":33,"offY":36,"sourceW":400,"sourceH":400},"ac_ransackTraitor_ani15":{"x":1054,"y":336,"w":346,"h":348,"offX":35,"offY":36,"sourceW":400,"sourceH":400},"ac_ransackTraitor_ani16":{"x":658,"y":2,"w":320,"h":324,"offX":40,"offY":44,"sourceW":400,"sourceH":400},"ac_ransackTraitor_ani17":{"x":2,"y":2,"w":330,"h":310,"offX":27,"offY":53,"sourceW":400,"sourceH":400},"ac_ransackTraitor_ani2":{"x":348,"y":328,"w":346,"h":342,"offX":51,"offY":35,"sourceW":400,"sourceH":400},"ac_ransackTraitor_ani3":{"x":1062,"y":686,"w":368,"h":358,"offX":32,"offY":22,"sourceW":400,"sourceH":400},"ac_ransackTraitor_ani4":{"x":384,"y":1044,"w":384,"h":368,"offX":16,"offY":19,"sourceW":400,"sourceH":400},"ac_ransackTraitor_ani5":{"x":696,"y":334,"w":356,"h":346,"offX":19,"offY":36,"sourceW":400,"sourceH":400},"ac_ransackTraitor_ani6":{"x":1128,"y":1046,"w":362,"h":374,"offX":13,"offY":13,"sourceW":400,"sourceH":400},"ac_ransackTraitor_ani7":{"x":708,"y":686,"w":352,"h":356,"offX":9,"offY":30,"sourceW":400,"sourceH":400},"ac_ransackTraitor_ani8":{"x":1308,"y":2,"w":332,"h":332,"offX":25,"offY":51,"sourceW":400,"sourceH":400},"ac_ransackTraitor_ani9":{"x":2,"y":1034,"w":380,"h":366,"offX":17,"offY":33,"sourceW":400,"sourceH":400}}}