{"file":"newyearlihuagreenfire.png","frames":{"newyearlihuagreenfire1":{"x":176,"y":344,"w":74,"h":70,"offX":37,"offY":385,"sourceW":150,"sourceH":500},"newyearlihuagreenfire10":{"x":176,"y":416,"w":58,"h":68,"offX":37,"offY":20,"sourceW":150,"sourceH":500},"newyearlihuagreenfire2":{"x":2,"y":364,"w":78,"h":138,"offX":36,"offY":317,"sourceW":150,"sourceH":500},"newyearlihuagreenfire3":{"x":252,"y":320,"w":84,"h":204,"offX":33,"offY":251,"sourceW":150,"sourceH":500},"newyearlihuagreenfire4":{"x":356,"y":232,"w":96,"h":292,"offX":25,"offY":163,"sourceW":150,"sourceH":500},"newyearlihuagreenfire5":{"x":128,"y":2,"w":110,"h":340,"offX":18,"offY":95,"sourceW":150,"sourceH":500},"newyearlihuagreenfire6":{"x":2,"y":2,"w":124,"h":360,"offX":13,"offY":29,"sourceW":150,"sourceH":500},"newyearlihuagreenfire7":{"x":240,"y":2,"w":114,"h":316,"offX":35,"offY":8,"sourceW":150,"sourceH":500},"newyearlihuagreenfire8":{"x":356,"y":2,"w":112,"h":228,"offX":33,"offY":11,"sourceW":150,"sourceH":500},"newyearlihuagreenfire9":{"x":82,"y":364,"w":92,"h":128,"offX":31,"offY":13,"sourceW":150,"sourceH":500}}}