{"SubTexture":[{"width":270,"y":1,"height":328,"name":"zhuowen_37","x":444},{"width":441,"y":1,"height":374,"name":"zhuowen_36","x":1},{"width":213,"y":569,"height":236,"name":"zhuowen_35","x":234},{"width":46,"y":569,"height":51,"name":"zhuowen_34","x":651},{"width":79,"y":1,"height":251,"name":"zhuowen_33","x":893},{"width":90,"y":836,"height":146,"name":"zhuowen_32","x":126},{"width":106,"y":597,"height":237,"name":"zhuowen_31","x":126},{"width":90,"y":807,"height":153,"name":"zhuowen_30","x":234},{"width":74,"y":723,"height":215,"name":"zhuowen_29","x":449},{"width":123,"y":597,"height":361,"name":"zhuowen_28","x":1},{"width":111,"y":362,"height":359,"name":"zhuowen_27","x":865},{"width":175,"y":1,"height":359,"name":"zhuowen_26","x":716},{"width":66,"y":825,"height":112,"name":"zhuowen_25","x":525},{"width":73,"y":569,"height":254,"name":"zhuowen_24","x":576},{"width":75,"y":807,"height":124,"name":"zhuowen_23","x":326},{"width":163,"y":362,"height":339,"name":"zhuowen_22","x":700},{"width":15,"y":658,"height":33,"name":"zhuowen_21","x":682},{"width":125,"y":569,"height":150,"name":"zhuowen_20","x":449},{"width":34,"y":997,"height":19,"name":"zhuowen_19","x":449},{"width":34,"y":997,"height":20,"name":"zhuowen_18","x":413},{"width":18,"y":864,"height":38,"name":"zhuowen_17","x":593},{"width":19,"y":807,"height":94,"name":"zhuowen_16","x":425},{"width":20,"y":807,"height":124,"name":"zhuowen_15","x":403},{"width":41,"y":721,"height":73,"name":"zhuowen_14","x":525},{"width":39,"y":962,"height":38,"name":"zhuowen_13","x":282},{"width":153,"y":377,"height":171,"name":"zhuowen_12","x":234},{"width":42,"y":622,"height":34,"name":"zhuowen_11","x":651},{"width":54,"y":825,"height":37,"name":"zhuowen_10","x":593},{"width":29,"y":658,"height":36,"name":"zhuowen_9","x":651},{"width":254,"y":331,"height":236,"name":"zhuowen_8","x":444},{"width":86,"y":939,"height":79,"name":"zhuowen_7","x":525},{"width":54,"y":703,"height":166,"name":"zhuowen_6","x":651},{"width":32,"y":933,"height":62,"name":"zhuowen_5","x":413},{"width":39,"y":796,"height":18,"name":"zhuowen_4","x":525},{"width":62,"y":962,"height":38,"name":"zhuowen_3","x":218},{"width":85,"y":933,"height":79,"name":"zhuowen_2","x":326},{"width":231,"y":377,"height":218,"name":"zhuowen_1","x":1}],"width":1024,"height":1024,"name":"wife_full3_2371","imagePath":"wife_full3_2371_tex.png"}