{"width":1024,"SubTexture":[{"width":58,"y":1,"height":232,"name":"youyi","x":689},{"width":163,"y":1,"height":292,"name":"houfa","x":1},{"width":158,"y":1,"height":292,"name":"body","x":166},{"frameWidth":17,"y":478,"frameHeight":27,"width":16,"frameX":-1,"height":26,"name":"shi1","frameY":-1,"x":152},{"frameWidth":16,"y":478,"frameHeight":23,"width":15,"frameX":-1,"height":21,"name":"shi2","frameY":-1,"x":207},{"frameWidth":18,"y":478,"frameHeight":24,"width":16,"frameX":-1,"height":23,"name":"shi3","frameY":-1,"x":170},{"frameWidth":18,"y":478,"frameHeight":21,"width":17,"frameX":-1,"height":20,"name":"shi4","frameY":-1,"x":188},{"frameWidth":124,"y":301,"frameHeight":156,"width":122,"frameX":-1,"height":155,"name":"face","frameY":-1,"x":552},{"width":48,"y":1,"height":128,"name":"fa2","x":749},{"width":88,"y":419,"height":88,"name":"fa1","x":1},{"width":59,"y":478,"height":21,"name":"yanpi","x":91},{"width":88,"y":1,"height":385,"name":"yifu","x":326},{"width":86,"y":1,"height":298,"name":"zuobi2","x":601},{"frameWidth":39,"y":388,"frameHeight":42,"width":38,"frameX":-1,"height":40,"name":"zuoshou","frameY":-1,"x":374},{"width":134,"y":156,"height":187,"name":"zuobi1","x":416},{"width":130,"y":388,"height":100,"name":"qundi","x":242},{"frameWidth":85,"y":301,"frameHeight":114,"width":83,"frameX":-1,"height":113,"name":"zuotui","frameY":-1,"x":758},{"width":239,"y":295,"height":122,"name":"youtui","x":1},{"width":183,"y":1,"height":153,"name":"body2","x":416},{"width":80,"y":301,"height":157,"name":"youbi2","x":676},{"width":83,"y":419,"height":57,"name":"youshou","x":91},{"width":119,"y":345,"height":157,"name":"youbi1","x":416}],"height":1024,"name":"wife_full3_2211","imagePath":"wife_full3_2211_tex.png"}