{"file":"composebiglv_anim_35.png","frames":{"composebiglv35_attack1":{"x":2,"y":144,"w":96,"h":136,"offX":46,"offY":40,"sourceW":180,"sourceH":180},"composebiglv35_attack2":{"x":194,"y":274,"w":96,"h":134,"offX":37,"offY":42,"sourceW":180,"sourceH":180},"composebiglv35_attack3":{"x":2,"y":2,"w":120,"h":140,"offX":45,"offY":36,"sourceW":180,"sourceH":180},"composebiglv35_death1":{"x":2,"y":282,"w":136,"h":80,"offX":16,"offY":99,"sourceW":180,"sourceH":180},"composebiglv35_standby":{"x":2,"y":144,"w":96,"h":136,"offX":46,"offY":40,"sourceW":180,"sourceH":180},"composebiglv35_walk1":{"x":292,"y":274,"w":90,"h":134,"offX":21,"offY":41,"sourceW":180,"sourceH":180},"composebiglv35_walk2":{"x":316,"y":2,"w":90,"h":134,"offX":21,"offY":41,"sourceW":180,"sourceH":180},"composebiglv35_walk3":{"x":124,"y":2,"w":92,"h":136,"offX":22,"offY":39,"sourceW":180,"sourceH":180},"composebiglv35_walk4":{"x":218,"y":138,"w":96,"h":134,"offX":19,"offY":40,"sourceW":180,"sourceH":180},"composebiglv35_walk5":{"x":218,"y":2,"w":96,"h":134,"offX":19,"offY":40,"sourceW":180,"sourceH":180},"composebiglv35_walk6":{"x":100,"y":144,"w":92,"h":136,"offX":21,"offY":39,"sourceW":180,"sourceH":180}}}